thermox/__init__.py
thermox/conditional.py
thermox/linalg.py
thermox/prob.py
thermox/sampler.py
thermox/utils.py
thermox-0.0.5.dist-info/LICENSE
thermox-0.0.5.dist-info/METADATA
thermox-0.0.5.dist-info/WHEEL
thermox-0.0.5.dist-info/top_level.txt
thermox-0.0.5.dist-info/RECORD
