Metadata-Version: 2.2
Name: thermox
Version: 0.0.5
Summary: Exact OU processes with JAX
Author-email: Sam Duffield <sam@normalcomputing.ai>, Kaelan Donatella <kaelan@normalcomputing.ai>
License: Apache-2.0
Keywords: jax,linear algebra,ou process,stochastic process
Classifier: Programming Language :: Python :: 3
Classifier: Topic :: Scientific/Engineering :: Mathematics
Classifier: License :: OSI Approved :: Apache Software License
Requires-Python: >=3.9
License-File: LICENSE
Requires-Dist: jax>=0.4.0
Requires-Dist: jaxlib>=0.4.0
Requires-Dist: fmmax>=1.1.1
Provides-Extra: test
Requires-Dist: pre-commit; extra == "test"
Requires-Dist: pytest-cov; extra == "test"
Requires-Dist: ruff; extra == "test"
Requires-Dist: optax; extra == "test"
Requires-Dist: mypy; extra == "test"
